setup.py
BusNetPy/ChineseAdminiDivisionsDict.py
BusNetPy/WGS1984.py
BusNetPy/__init__.py
BusNetPy/busbuild.py
BusNetPy/buslist.py
BusNetPy/buspider.py
BusNetPy/citybus.py
BusNetPy/citycode.py
BusNetPy/conversion_geo.py
BusNetPy/csvis.py
BusNetPy/find_cycle.py
BusNetPy/metrical.py
BusNetPy.egg-info/PKG-INFO
BusNetPy.egg-info/SOURCES.txt
BusNetPy.egg-info/dependency_links.txt
BusNetPy.egg-info/requires.txt
BusNetPy.egg-info/top_level.txt