Metadata-Version: 2.1
Name: BusNetPy
Version: 1.0.0
Summary: busplanner
Author: jinyangLi
Author-email: 1045186183@qq.com
License: MIT
Requires-Dist: pandas>=2.0.3
Requires-Dist: geopandas>=0.13.2
Requires-Dist: shapely>=2.0.2
Requires-Dist: requests>=2.31.0
Requires-Dist: contextily>=1.5.2
Requires-Dist: matplotlib>=3.7.4
Requires-Dist: osmnx>=1.9.1
Requires-Dist: urllib3>=1.26.18
Requires-Dist: xlwt>=1.3.0
Requires-Dist: tqdm>=4.66.1
Requires-Dist: fuzzywuzzy>=0.18.0
Requires-Dist: bs4>=0.0.2
Requires-Dist: pypinyin>=0.49.0
Requires-Dist: networkx>=3.1
